dbit/__init__.py
dbit/cli.py
dbit/cli_help.py
dbit/database.py
dbit/commands/__init__.py
dbit/commands/connect.py
dbit/commands/diff.py
dbit/commands/disconnect.py
dbit/commands/init.py
dbit/commands/log.py
dbit/commands/snapshot.py
dbit/commands/status.py
dbit/commands/verify.py
dbit/utils/__init__.py
dbit/utils/diff.py
dbit/utils/rules.py
dbit-0.1.1.dist-info/licenses/LICENSE
dbit-0.1.1.dist-info/METADATA
dbit-0.1.1.dist-info/WHEEL
dbit-0.1.1.dist-info/entry_points.txt
dbit-0.1.1.dist-info/top_level.txt
dbit-0.1.1.dist-info/RECORD
