Metadata-Version: 2.4
Name: dbit
Version: 0.1.1
Summary: Git-like CLI tool for database schema version control with multi-database support
Author-email: Navaneet <navaneetnr@gmail.com>
Maintainer-email: Navaneet <navaneetnr@gmail.com>
License: MIT
Project-URL: Homepage, https://github.com/nrnavaneet/dbit
Project-URL: Documentation, https://github.com/nrnavaneet/dbit/tree/main/docs
Project-URL: Changelog, https://github.com/nrnavaneet/dbit/blob/main/CHANGELOG.md
Project-URL: Issues, https://github.com/nrnavaneet/dbit/issues
Project-URL: Discussions, https://github.com/nrnavaneet/dbit/discussions
Keywords: database,schema,version-control,migration,git,postgresql,mysql,sqlite,devops,database-management
Classifier: Development Status :: 4 - Beta
Classifier: Intended Audience :: Developers
Classifier: Intended Audience :: System Administrators
Classifier: Topic :: Database
Classifier: Topic :: Software Development :: Version Control
Classifier: Topic :: System :: Systems Administration
Classifier: Programming Language :: Python :: 3
Classifier: Programming Language :: Python :: 3.8
Classifier: Programming Language :: Python :: 3.9
Classifier: Programming Language :: Python :: 3.10
Classifier: Programming Language :: Python :: 3.11
Classifier: Programming Language :: Python :: 3.12
Classifier: Programming Language :: Python :: 3.13
Classifier: Operating System :: OS Independent
Classifier: Environment :: Console
Classifier: Natural Language :: English
Requires-Python: >=3.8
License-File: LICENSE
Requires-Dist: click>=8.0.0
Requires-Dist: pyyaml>=6.0
Requires-Dist: sqlparse>=0.4.0
Requires-Dist: psycopg2-binary>=2.9.0
Requires-Dist: mysql-connector-python>=8.0.0
Requires-Dist: SQLAlchemy<3.0.0,>=1.4.0
Provides-Extra: dev
Requires-Dist: pytest>=7.0.0; extra == "dev"
Requires-Dist: black>=22.0.0; extra == "dev"
Requires-Dist: isort>=5.10.0; extra == "dev"
Requires-Dist: flake8>=4.0.0; extra == "dev"
Requires-Dist: pre-commit>=3.0.0; extra == "dev"
Dynamic: license-file
